forgive/__init__.py
forgive/db.py
forgive-1.0.0.dist-info/DESCRIPTION.rst
forgive-1.0.0.dist-info/METADATA
forgive-1.0.0.dist-info/RECORD
forgive-1.0.0.dist-info/WHEEL
forgive-1.0.0.dist-info/metadata.json
forgive-1.0.0.dist-info/top_level.txt
