Metadata-Version: 2.0
Name: forgive
Version: 1.0.0
Summary: Coding should be simple and fun. Certainly I will choose ForgiveDB.
Home-page: https://github.com/hui-z/ForgiveDB
Author: Lirian Su
Author-email: liriansu@gmail.com
License: WTFPL
Platform: UNKNOWN
